CHANGES.md
MANIFEST.in
README.md
setup.py
lib/django_markdown_deux.egg-info/PKG-INFO
lib/django_markdown_deux.egg-info/SOURCES.txt
lib/django_markdown_deux.egg-info/dependency_links.txt
lib/django_markdown_deux.egg-info/not-zip-safe
lib/django_markdown_deux.egg-info/requires.txt
lib/django_markdown_deux.egg-info/top_level.txt
lib/markdown_deux/__init__.py
lib/markdown_deux/conf/__init__.py
lib/markdown_deux/conf/settings.py
lib/markdown_deux/templates/markdown_deux/markdown_cheatsheet.html
lib/markdown_deux/templatetags/__init__.py
lib/markdown_deux/templatetags/markdown_deux_tags.py