Metadata-Version: 1.0
Name: django-markdown-deux
Version: 1.0.3
Summary: a Django app that provides template tags for using Markdown (using the python-markdown2 processor)
Home-page: http://github.com/trentm/django-markdown-deux
Author: Trent Mick
Author-email: trentm@gmail.com
License: MIT
Keywords: django markdown markdown2 text markup html
Platform: UNKNOWN
Classifier: Development Status :: 5 - Production/Stable
Classifier: Environment :: Web Environment
Classifier: Framework :: Django
Classifier: Intended Audience :: Developers
Classifier: License :: OSI Approved :: MIT License
Classifier: Operating System :: OS Independent
Classifier: Programming Language :: Python :: 2
Classifier: Topic :: Internet :: WWW/HTTP
